pipe.v
module PipelinedProcessor(
    input clk, reset,
    input [31:0] instruction_in, // Instruction from instruction memory
    input [31:0] data_in,        // Data from data memory
    output reg [31:0] data_out,  // Data to be written back
    output reg [31:0] address_out // Address to access memory
);
    // Pipeline registers
    reg [31:0] IF_ID_instr, IF_ID_pc;
    reg [31:0] ID_EX_regA, ID_EX_regB, ID_EX_instr;
    reg [31:0] EX_MEM_alu_out, EX_MEM_instr;
    reg [31:0] MEM_WB_data, MEM_WB_alu_out, MEM_WB_instr;

    // Registers and memory
    reg [31:0] register_file[0:15]; // 16 general-purpose registers
    reg [31:0] pc;

    // Instruction fields
    wire [3:0] opcode = IF_ID_instr[31:28];
    wire [3:0] rs = IF_ID_instr[27:24];
    wire [3:0] rt = IF_ID_instr[23:20];
    wire [3:0] rd = IF_ID_instr[19:16];
    wire [15:0] imm = IF_ID_instr[15:0];

    // ALU control signals
    reg [31:0] alu_in1, alu_in2, alu_out;

    // Stage 1: Instruction Fetch (IF)
    always @(posedge clk or posedge reset) begin
        if (reset) begin
            pc <= 0;
            IF_ID_instr <= 0;
            IF_ID_pc <= 0;
        end else begin
            IF_ID_instr <= instruction_in;
            IF_ID_pc <= pc;
            pc <= pc + 4;
        end
    end

    // Stage 2: Instruction Decode (ID)
    always @(posedge clk or posedge reset) begin
        if (reset) begin
            ID_EX_instr <= 0;
            ID_EX_regA <= 0;
            ID_EX_regB <= 0;
        end else begin
            ID_EX_instr <= IF_ID_instr;
            ID_EX_regA <= register_file[rs];
            ID_EX_regB <= opcode == 4'b1000 ? imm : register_file[rt]; // LOAD uses immediate
        end
    end

    // Stage 3: Execute (EX)
    always @(posedge clk or posedge reset) begin
        if (reset) begin
            EX_MEM_alu_out <= 0;
            EX_MEM_instr <= 0;
        end else begin
            case (opcode)
                4'b0000: alu_out <= ID_EX_regA + ID_EX_regB; // ADD
                4'b0001: alu_out <= ID_EX_regA - ID_EX_regB; // SUB
                4'b0010: alu_out <= ID_EX_regA & ID_EX_regB; // AND
                4'b1000: alu_out <= ID_EX_regA + ID_EX_regB; // LOAD: Address calculation
                default: alu_out <= 0;
            endcase
            EX_MEM_alu_out <= alu_out;
            EX_MEM_instr <= ID_EX_instr;
        end
    end

    // Stage 4: Memory/Write Back (MEM/WB)
    always @(posedge clk or posedge reset) begin
        if (reset) begin
            MEM_WB_data <= 0;
            MEM_WB_alu_out <= 0;
            MEM_WB_instr <= 0;
        end else begin
            if (opcode == 4'b1000) begin
                MEM_WB_data <= data_in; // LOAD
            end else begin
                MEM_WB_alu_out <= EX_MEM_alu_out; // Write ALU result
            end
            MEM_WB_instr <= EX_MEM_instr;
            register_file[rd] <= (opcode == 4'b1000) ? MEM_WB_data : MEM_WB_alu_out; // Write back result
        end
    end

    // Output signals
    always @(*) begin
        data_out = MEM_WB_data;
        address_out = EX_MEM_alu_out;
    end
endmodule

pipe_tb.v
module tb_PipelinedProcessor;
    reg clk, reset;
    reg [31:0] instruction_in, data_in;
    wire [31:0] data_out, address_out;

    // Instantiate the processor
    PipelinedProcessor uut (
        .clk(clk),
        .reset(reset),
        .instruction_in(instruction_in),
        .data_in(data_in),
        .data_out(data_out),
        .address_out(address_out)
    );

    // Clock generation
    initial begin
        clk = 0;
        forever #5 clk = ~clk; // 10ns clock period
    end

    // Test stimulus
    initial begin
        reset = 1;
        instruction_in = 0;
        data_in = 0;

        #10 reset = 0;

        // Test ADD R1 = R2 + R3
        #10 instruction_in = {4'b0000, 4'b0010, 4'b0011, 4'b0001, 16'b0}; // ADD R1, R2, R3

        // Test SUB R4 = R5 - R6
        #10 instruction_in = {4'b0001, 4'b0101, 4'b0110, 4'b0100, 16'b0}; // SUB R4, R5, R6

        // Test AND R7 = R8 & R9
        #10 instruction_in = {4'b0010, 4'b1000, 4'b1001, 4'b0111, 16'b0}; // AND R7, R8, R9

        // Test LOAD R10 = MEM[R11 + 4]
        #10 instruction_in = {4'b1000, 4'b1011, 4'b0000, 4'b1010, 16'b0000_0000_0000_0100}; // LOAD R10, 4(R11)
        data_in = 32'hDEADBEEF; // Simulate memory returning data

        #50 $stop;
    end

    initial begin
        $dumpfile("dump.vcd");
        $dumpvars(0);
    end

endmodule

dump.vcd
$date
	Mon Dec 30 13:24:03 2024
$end
$version
	Icarus Verilog
$end
$timescale
	1s
$end
$scope module tb_PipelinedProcessor $end
$var wire 32 ! data_out [31:0] $end
$var wire 32 " address_out [31:0] $end
$var reg 1 # clk $end
$var reg 32 $ data_in [31:0] $end
$var reg 32 % instruction_in [31:0] $end
$var reg 1 & reset $end
$scope module uut $end
$var wire 1 # clk $end
$var wire 32 ' data_in [31:0] $end
$var wire 32 ( instruction_in [31:0] $end
$var wire 1 & reset $end
$var wire 4 ) rt [3:0] $end
$var wire 4 * rs [3:0] $end
$var wire 4 + rd [3:0] $end
$var wire 4 , opcode [3:0] $end
$var wire 16 - imm [15:0] $end
$var reg 32 . EX_MEM_alu_out [31:0] $end
$var reg 32 / EX_MEM_instr [31:0] $end
$var reg 32 0 ID_EX_instr [31:0] $end
$var reg 32 1 ID_EX_regA [31:0] $end
$var reg 32 2 ID_EX_regB [31:0] $end
$var reg 32 3 IF_ID_instr [31:0] $end
$var reg 32 4 IF_ID_pc [31:0] $end
$var reg 32 5 MEM_WB_alu_out [31:0] $end
$var reg 32 6 MEM_WB_data [31:0] $end
$var reg 32 7 MEM_WB_instr [31:0] $end
$var reg 32 8 address_out [31:0] $end
$var reg 32 9 alu_out [31:0] $end
$var reg 32 : data_out [31:0] $end
$var reg 32 ; pc [31:0] $end
$upscope $end
$upscope $end
$enddefinitions $end
$comment Show the parameter values. $end
$dumpall
$end
#0
$dumpvars
b0 ;
b0 :
bx 9
b0 8
b0 7
b0 6
b0 5
b0 4
b0 3
b0 2
b0 1
b0 0
b0 /
b0 .
b0 -
b0 ,
b0 +
b0 *
b0 )
b0 (
b0 '
1&
b0 %
b0 $
0#
b0 "
b0 !
$end
#5
1#
#10
0#
0&
#15
bx "
bx 8
b100 ;
bx 2
bx 1
bx .
b0 9
1#
#20
0#
b10001100010000000000000000 %
b10001100010000000000000000 (
#25
b0 "
b0 8
b10 *
b11 )
b1 +
bx 5
b0 .
bx 9
b0 2
b0 1
b1000 ;
b100 4
b10001100010000000000000000 3
1#
#30
0#
b10101011001000000000000000000 %
b10101011001000000000000000000 (
#35
b1 ,
b101 *
b110 )
b100 +
bx "
bx 8
b1100 ;
b1000 4
b10101011001000000000000000000 3
bx 2
bx 1
b10001100010000000000000000 0
bx .
b0 9
b0 5
1#
#40
0#
b101000100101110000000000000000 %
b101000100101110000000000000000 (
#45
b0 "
b0 8
b10 ,
b1000 *
b1001 )
b111 +
bx 5
b10001100010000000000000000 /
b0 .
bx 9
b10101011001000000000000000000 0
b10000 ;
b1100 4
b101000100101110000000000000000 3
1#
#50
0#
b11011110101011011011111011101111 $
b11011110101011011011111011101111 '
b10001011000010100000000000000100 %
b10001011000010100000000000000100 (
#55
b1000 ,
b1011 *
b0 )
b1010 +
b100 -
bx "
bx 8
b10100 ;
b10000 4
b10001011000010100000000000000100 3
b101000100101110000000000000000 0
b10101011001000000000000000000 /
bx .
b10001100010000000000000000 7
b0 5
1#
#60
0#
#65
b11011110101011011011111011101111 !
b11011110101011011011111011101111 :
b10101011001000000000000000000 7
b11011110101011011011111011101111 6
b101000100101110000000000000000 /
b100 2
b10001011000010100000000000000100 0
b11000 ;
b10100 4
1#
#70
0#
#75
b11100 ;
b11000 4
b10001011000010100000000000000100 /
b101000100101110000000000000000 7
1#
#80
0#
#85
b10001011000010100000000000000100 7
b100000 ;
b11100 4
1#
#90
0#
#95
b100100 ;
b100000 4
1#
